TADLib-0.4.5.post1.data/scripts/calfea
TADLib-0.4.5.post1.data/scripts/domaincaller
TADLib-0.4.5.post1.data/scripts/hitad
TADLib-0.4.5.post1.data/scripts/output-DI
TADLib-0.4.5.post1.data/scripts/tad-plot
tadlib/__init__.py
tadlib/calfea/__init__.py
tadlib/calfea/analyze.py
tadlib/calfea/polygon.py
tadlib/domaincaller/__init__.py
tadlib/domaincaller/chromLev.py
tadlib/domaincaller/genomeLev.py
tadlib/hitad/__init__.py
tadlib/hitad/aligner.py
tadlib/hitad/chromLev.py
tadlib/hitad/genomeLev.py
tadlib/hitad/graph.py
tadlib/visualize/__init__.py
tadlib/visualize/heatmaps.py
TADLib-0.4.5.post1.dist-info/LICENSE
TADLib-0.4.5.post1.dist-info/METADATA
TADLib-0.4.5.post1.dist-info/WHEEL
TADLib-0.4.5.post1.dist-info/top_level.txt
TADLib-0.4.5.post1.dist-info/RECORD
