Metadata-Version: 2.1
Name: TADLib
Version: 0.4.5.post1
Summary: A Library to Explore Chromatin Interaction Patterns for Topologically Associating Domains
Home-page: https://github.com/XiaoTaoWang/TADLib/
Author: XiaoTao Wang
Author-email: wangxiaotao686@gmail.com
License: UNKNOWN
Keywords: TAD Aggregation Preference AP sub-TAD hierarchy Hi-C cooler
Platform: UNKNOWN
Classifier: Programming Language :: Python
Classifier: License :: OSI Approved :: GNU General Public License v3 or later (GPLv3+)
Classifier: Operating System :: POSIX
Classifier: Development Status :: 3 - Alpha
Classifier: Intended Audience :: Science/Research
Classifier: Topic :: Scientific/Engineering :: Bio-Informatics
